{
  "apiVersion": "v5",
  "AUTH_SECRET": "secret",
  "logLevel": "info",
  "version": "v5",
  "captureLogs": "false",
  "enableFileUpload": "true",
  "logentriesToken": "",
  "pubsubQueueName": "project.service",
  "pubsubExchangeName": "projects",
  "fileServiceEndpoint": "",
  "identityServiceEndpoint": "",
  "memberServiceEndpoint": "",
  "directProjectServiceEndpoint": "",
  "directProjectServiceTimeout": 5000,
  "attachmentsS3Bucket": "topcoder-prod-media",
  "projectAttachmentPathPrefix": "projects",
  "projectAttachmentPathSuffix": "attachments",
  "elasticsearchConfig": {
    "host": "",
    "apiVersion": "6.8",
    "indexName": "projects",
    "docType": "doc",
    "timelineIndexName": "timelines",
    "timelineDocType": "doc",
    "metadataIndexName": "metadata",
    "metadataDocType": "doc",
    "metadataDocDefaultId": 1
  },
  "connectProjectUrl":"",
  "dbConfig": {
    "masterUrl": "",
    "maxPoolSize": 50,
    "minPoolSize": 4,
    "idleTimeout": 1000
  },
  "kafkaConfig": {
    "url": "localhost:9092"
  },
  "analyticsKey": "",
  "VALID_ISSUERS": "[\"https:\/\/topcoder-newauth.auth0.com\/\",\"https:\/\/api.topcoder-dev.com\",\"https:\/\/topcoder-dev.auth0.com\/\"]",
  "validIssuers": "[\"https:\/\/topcoder-newauth.auth0.com\/\",\"https:\/\/api.topcoder-dev.com\",\"https:\/\/topcoder-dev.auth0.com\/\"]",
  "jwksUri": "",
  "busApiUrl": "http://api.topcoder-dev.com/v5",
  "messageApiUrl": "http://api.topcoder-dev.com/v5",
  "busApiToken": "eyJhbGciOiJIUzI1NiIsInR5cCI6IkpXVCJ9.eyJuYW1lIjoicHJvamVjdC1zZXJ2aWNlIiwiaWF0IjoxNTEyNzQ3MDgyLCJleHAiOjE1MjEzODcwODJ9.PHuNcFDaotGAL8RhQXQMdpL8yOKXxjB5DbBIodmt7RE",
  "HEALTH_CHECK_URL": "_health",
  "maxPhaseProductCount": 1,
  "TOKEN_CACHE_TIME": "86000",
  "whitelistedOriginsForUserIdAuth": "[\"https:\/\/topcoder-newauth.auth0.com\/\",\"https:\/\/api.topcoder-dev.com\"]",
  "EMAIL_INVITE_FROM_NAME":"Topcoder",
  "EMAIL_INVITE_FROM_EMAIL":"noreply@connect.topcoder.com",
  "inviteEmailSubject": "You are invited to Topcoder",
  "inviteEmailSectionTitle": "Project Invitation",
  "connectUrl":"https://connect.topcoder-dev.com",
  "accountsAppUrl": "https://accounts.topcoder-dev.com",
  "MAX_REVISION_NUMBER": 100,
  "UNIQUE_GMAIL_VALIDATION": false,
  "pageSize": 20,
  "VALID_STATUSES_BEFORE_PAUSED": "[\"active\"]",
  "SSO_REFCODES": "[]",
  "lookerConfig": {
    "EMBED_KEY": "FAKE_KEY",
    "LOOKER_HOST": "demo.looker.com",
    "SESSION_LENGTH": 120,
    "BASE_URL": "",
    "CLIENT_ID": "",
    "CLIENT_SECRET": "",
    "TOKEN": "TOKEN",
    "USE_MOCK": "true",
    "QUERIES": {
      "REG_STATS": 1234,
      "BUDGET": 123
    },
    "EMBED_REPORTS_MAPPING": "{\"mock\": \"/embed/looks/2\"}",
    "ALLOWED_USERS": "[]"
  },
  "DEFAULT_M2M_USERID": -101
}
